{"profileUrl": "/display/sashabw", "mostSpecificTypes": ["Adjunct Faculty"], "name": "Sasha Harris", "label": "Sasha Harris", "URI": "http://scholars.uab.edu/individual/sashabw", "preferredTitle": "Director-Nursing Services", "shortViewHtml": "\n<li class=\"individual\" role=\"listitem\" role=\"navigation\">\n\n    <h2>\n        <a href=\"/display/sashabw\" title=\"View the profile page for Sasha Harris\">Sasha Harris</a>\n    </h2>\n\n    <span class=\"title\">Director-Nursing Services</span>\n\n</li>\n", "email": ["sashabw@uab.edu"], "phone": [], "position": [",Instructor - Adjunct (P),,,Nursing Academic Support,,,,Nursing Academic Affairs,,"]}