{"profileUrl": "/display/cbanks71", "mostSpecificTypes": ["Adjunct Faculty"], "name": "Charles Banks Jr.", "label": "Charles Banks Jr.", "URI": "http://scholars.uab.edu/individual/cbanks71", "preferredTitle": "Adjunct Instructor", "shortViewHtml": "\n<li class=\"individual\" role=\"listitem\" role=\"navigation\">\n\n    <h2>\n        <a href=\"/display/cbanks71\" title=\"View the profile page for Charles Banks Jr.\">Charles Banks Jr.</a>\n    </h2>\n\n    <span class=\"title\">Adjunct Instructor</span>\n\n</li>\n", "email": ["cbanks71@uab.edu"], "phone": [], "position": [",Instructor - Adjunct (P),,,General Dentistry,,,,School of Dentistry,,"]}