{"profileUrl": "/display/ttrulove", "mostSpecificTypes": ["Adjunct Faculty"], "name": "Timothy Trulove", "label": "Timothy Trulove", "URI": "http://scholars.uab.edu/individual/ttrulove", "preferredTitle": "Adjunct Associate Professor", "shortViewHtml": "\n<li class=\"individual\" role=\"listitem\" role=\"navigation\">\n\n    <h2>\n        <a href=\"/display/ttrulove\" title=\"View the profile page for Timothy Trulove\">Timothy Trulove</a>\n    </h2>\n\n    <span class=\"title\">Adjunct Associate Professor</span>\n\n</li>\n", "email": ["ttrulove@uab.edu"], "phone": [], "position": [",Associate Professor - Adjunct (P),,,Orthodontics,,,,School of Dentistry,,"]}