{"profileUrl": "/display/nakazawk", "mostSpecificTypes": ["Adjunct Faculty"], "imageUrl": "/file/nnakazawktdL77/nakazawk.jpg", "name": "Kazutoshi Nakazawa", "label": "Kazutoshi Nakazawa", "thumbUrl": "/file/nnakazawktdL77/nakazawk.jpg", "URI": "http://scholars.uab.edu/individual/nakazawk", "preferredTitle": "Adjunct Associate Professor", "shortViewHtml": "\n<li class=\"individual\" role=\"listitem\" role=\"navigation\">\n\n    <img src=\"/file/nnakazawktdL77/nakazawk.jpg\" width=\"90\" alt=\"Kazutoshi Nakazawa\" />\n    <h2 class=\"thumb\">\n        <a href=\"/display/nakazawk\" title=\"View the profile page for Kazutoshi Nakazawa\">Kazutoshi Nakazawa</a>\n    </h2>\n\n    <span class=\"title\">Adjunct Associate Professor</span>\n\n</li>\n", "email": ["nakazawk@uab.edu"], "phone": [], "position": [",Associate Professor - Adjunct (P),,,Neurobiology,,,,Academic Joint Departments,,"]}