{"profileUrl": "/display/cdb1908", "mostSpecificTypes": ["Adjunct Faculty"], "name": "Cinnamon Banks MSN, RN", "label": "Cinnamon Banks MSN, RN", "URI": "http://scholars.uab.edu/individual/cdb1908", "preferredTitle": "Adjunct Instructor", "shortViewHtml": "\n<li class=\"individual\" role=\"listitem\" role=\"navigation\">\n\n    <h2>\n        <a href=\"/display/cdb1908\" title=\"View the profile page for Cinnamon Banks MSN, RN\">Cinnamon Banks MSN, RN</a>\n    </h2>\n\n    <span class=\"title\">Adjunct Instructor</span>\n\n</li>\n", "email": ["cdb1908@uab.edu"], "phone": [], "position": [",Instructor - Adjunct (P),,,Nursing Academic Support,,,,Nursing Academic Affairs,,"]}