{"profileUrl": "/display/stephle", "mostSpecificTypes": ["Adjunct Faculty"], "name": "Laura Romundstad MSN, CRNP, AGPCNP-BC", "label": "Laura Romundstad MSN, CRNP, AGPCNP-BC", "URI": "http://scholars.uab.edu/individual/stephle", "preferredTitle": "Adjunct Instructor", "shortViewHtml": "\n<li class=\"individual\" role=\"listitem\" role=\"navigation\">\n\n    <h2>\n        <a href=\"/display/stephle\" title=\"View the profile page for Laura Romundstad MSN, CRNP, AGPCNP-BC\">Laura Romundstad MSN, CRNP, AGPCNP-BC</a>\n    </h2>\n\n    <span class=\"title\">Adjunct Instructor</span>\n\n</li>\n", "email": ["stephle@uab.edu"], "phone": [], "position": [",Instructor - Adjunct (P),,,Nursing Academic Support,,,,Nursing Academic Affairs,,"]}