{"profileUrl": "/display/dtucker", "mostSpecificTypes": ["Adjunct Faculty"], "imageUrl": "/file/ndtuckertdL77/dtucker.jpg", "name": "Diane Tucker Ph.D.", "label": "Diane Tucker Ph.D.", "thumbUrl": "/file/ndtuckertdL77/dtucker.jpg", "URI": "http://scholars.uab.edu/individual/dtucker", "preferredTitle": "Adjunct Professor", "shortViewHtml": "\n<li class=\"individual\" role=\"listitem\" role=\"navigation\">\n\n    <img src=\"/file/ndtuckertdL77/dtucker.jpg\" width=\"90\" alt=\"Diane Tucker Ph.D.\" />\n    <h2 class=\"thumb\">\n        <a href=\"/display/dtucker\" title=\"View the profile page for Diane Tucker Ph.D.\">Diane Tucker Ph.D.</a>\n    </h2>\n\n    <span class=\"title\">Adjunct Professor</span>\n\n</li>\n", "email": ["dtucker@uab.edu"], "phone": ["205-934-8885"], "position": [",Professor - Adjunct (P),,,Psychology,,,,College of Arts and Sciences,,"]}