{"profileUrl": "/display/wilson24", "mostSpecificTypes": ["Adjunct Faculty"], "name": "Joan Wilson MSN, CRNP, AGACNP-BC", "label": "Joan Wilson MSN, CRNP, AGACNP-BC", "URI": "http://scholars.uab.edu/individual/wilson24", "preferredTitle": "Adv Pract Provider-Acute/Emergency", "shortViewHtml": "\n<li class=\"individual\" role=\"listitem\" role=\"navigation\">\n\n    <h2>\n        <a href=\"/display/wilson24\" title=\"View the profile page for Joan Wilson MSN, CRNP, AGACNP-BC\">Joan Wilson MSN, CRNP, AGACNP-BC</a>\n    </h2>\n\n    <span class=\"title\">Adv Pract Provider-Acute/Emergency</span>\n\n</li>\n", "email": ["wilson24@uab.edu"], "phone": [], "position": [",Instructor - Adjunct (P),,,Nursing Academic Support,,,,Nursing Academic Affairs,,"]}