{"profileUrl": "/display/gbarsh", "mostSpecificTypes": ["Adjunct Faculty"], "name": "Greg Barsh", "label": "Greg Barsh", "URI": "http://scholars.uab.edu/individual/gbarsh", "preferredTitle": "Adjunct Professor", "shortViewHtml": "\n<li class=\"individual\" role=\"listitem\" role=\"navigation\">\n\n    <h2>\n        <a href=\"/display/gbarsh\" title=\"View the profile page for Greg Barsh\">Greg Barsh</a>\n    </h2>\n\n    <span class=\"title\">Adjunct Professor</span>\n\n</li>\n", "email": ["gbarsh@uab.edu"], "phone": [], "position": [",Professor - Adjunct (P),,,Genetics,,,,Academic Joint Departments,,"]}