{"profileUrl": "/display/johnmc", "mostSpecificTypes": ["Adjunct Faculty"], "name": "John McDonald", "label": "John McDonald", "URI": "http://scholars.uab.edu/individual/johnmc", "preferredTitle": "Adjunct Assistant Professor", "shortViewHtml": "\n<li class=\"individual\" role=\"listitem\" role=\"navigation\">\n\n    <h2>\n        <a href=\"/display/johnmc\" title=\"View the profile page for John McDonald\">John McDonald</a>\n    </h2>\n\n    <span class=\"title\">Adjunct Assistant Professor</span>\n\n</li>\n", "email": ["johnmc@uab.edu"], "phone": [], "position": []}