{"profileUrl": "/display/silasr14", "mostSpecificTypes": ["Adjunct Faculty"], "name": "Richard Reindollar", "label": "Richard Reindollar", "URI": "http://scholars.uab.edu/individual/silasr14", "preferredTitle": "Adjunct Professor", "shortViewHtml": "\n<li class=\"individual\" role=\"listitem\" role=\"navigation\">\n\n    <h2>\n        <a href=\"/display/silasr14\" title=\"View the profile page for Richard Reindollar\">Richard Reindollar</a>\n    </h2>\n\n    <span class=\"title\">Adjunct Professor</span>\n\n</li>\n", "email": ["silasr14@uab.edu"], "phone": [], "position": [",Professor - Adjunct (P),,,OB/GYN - Reproductive Endocrinology,,,,OB/GYN,,"]}