{"profileUrl": "/display/bshadoan", "mostSpecificTypes": ["Adjunct Faculty"], "name": "Beth Shadoan MSN, RN", "label": "Beth Shadoan MSN, RN", "URI": "http://scholars.uab.edu/individual/bshadoan", "preferredTitle": "Adjunct Instructor", "shortViewHtml": "\n<li class=\"individual\" role=\"listitem\" role=\"navigation\">\n\n    <h2>\n        <a href=\"/display/bshadoan\" title=\"View the profile page for Beth Shadoan MSN, RN\">Beth Shadoan MSN, RN</a>\n    </h2>\n\n    <span class=\"title\">Adjunct Instructor</span>\n\n</li>\n", "email": ["bshadoan@uab.edu"], "phone": [], "position": [",Instructor - Adjunct (P),,,Nursing Academic Support,,,,Nursing Academic Affairs,,"]}