{"profileUrl": "/display/mdconner", "mostSpecificTypes": ["Adjunct Faculty"], "name": "Mark Conner", "label": "Mark Conner", "URI": "http://scholars.uab.edu/individual/mdconner", "preferredTitle": "Adjunct Assistant Professor", "shortViewHtml": "\n<li class=\"individual\" role=\"listitem\" role=\"navigation\">\n\n    <h2>\n        <a href=\"/display/mdconner\" title=\"View the profile page for Mark Conner\">Mark Conner</a>\n    </h2>\n\n    <span class=\"title\">Adjunct Assistant Professor</span>\n\n</li>\n", "email": ["mdconner@uab.edu"], "phone": [], "position": [",Assistant Professor - Adjunct (P),,,Mechanical Engineering,,,,School of Engineering,,"]}